sixadsml/__init__.py
sixadsml/clean_text.py
sixadsml/embeddings.py
sixadsml/images.py
sixadsml/sql_utility.py
sixadsml/utility.py
SixAdsDS-0.1.6.dist-info/LICENSE.txt
SixAdsDS-0.1.6.dist-info/METADATA
SixAdsDS-0.1.6.dist-info/WHEEL
SixAdsDS-0.1.6.dist-info/top_level.txt
SixAdsDS-0.1.6.dist-info/RECORD
