Metadata-Version: 2.1
Name: SixAdsDS
Version: 0.1.6
Summary: Generic functions for SixAds data science projects
Home-page: https://bitbucket.org/eligijus112/sixadsml/
Author: Eligijus Bujokas
Author-email: eligijus@sixads.net
License: UNKNOWN
Platform: UNKNOWN
Classifier: Programming Language :: Python :: 3
Classifier: License :: OSI Approved :: MIT License
Classifier: Operating System :: OS Independent
Requires-Dist: inflection
Requires-Dist: nltk
Requires-Dist: pandas
Requires-Dist: sqlalchemy
Requires-Dist: PyYAML
Requires-Dist: keras
Requires-Dist: tensorflow
Requires-Dist: sklearn
Requires-Dist: tqdm
Requires-Dist: pymysql
Requires-Dist: opencv-python
Requires-Dist: Pillow
Requires-Dist: requests
